pylatex/__init__.py
pylatex/_version.py
pylatex/basic.py
pylatex/config.py
pylatex/document.py
pylatex/errors.py
pylatex/figure.py
pylatex/frames.py
pylatex/headfoot.py
pylatex/labelref.py
pylatex/lists.py
pylatex/math.py
pylatex/package.py
pylatex/position.py
pylatex/quantities.py
pylatex/section.py
pylatex/table.py
pylatex/tikz.py
pylatex/utils.py
pylatex/base_classes/__init__.py
pylatex/base_classes/command.py
pylatex/base_classes/containers.py
pylatex/base_classes/float.py
pylatex/base_classes/latex_object.py
pytex/__init__.py
pytex/core.py
pytex/document.py
pytex/mdtree.py
pytex/renderer.py
pytex/autodif/Tensor.py
pytex/autodif/__init__.py
pytex/autodif/main.py
pytex/autodif/variable.py
pytex/base/__init__.py
pytex/base/table.py
pytex/exam/__init__.py
pytex/exam/choice.py
pytex/exam/question.py
pytex/math/__init__.py
pytex/math/graph.py
pytex/math/main.py
pytex/math/symbol.py
pytex/math/tensor.py
pytex/math/utils.py
pytex/math/variable.py
pytex/paper/__init__.py
pytex/paper/abstract.py
pytex/paper/appendix.py
pytex/paper/doctree.py
pytex/paper/header.py
pytex/paper/section.py
pytex/utils/__init__.py
pytex/utils/md2tex.py
pytex/utils/pseudocode.py
pytex/utils/symbol2tex.py
pytex/utils/utils.py
bone_pytex-0.1.6.dist-info/LICENSE
bone_pytex-0.1.6.dist-info/METADATA
bone_pytex-0.1.6.dist-info/WHEEL
bone_pytex-0.1.6.dist-info/top_level.txt
bone_pytex-0.1.6.dist-info/RECORD
