Metadata-Version: 2.1
Name: bone-pytex
Version: 0.1.6
Summary: 一个用来简化LaTex编写的Python库
Home-page: https://github.com/tczrr1999/PyTex
Author: zrr
Author-email: 2742392377@qq.com
License: GPL-3.0 Licence
Keywords: LaTex,MarkDown
Platform: any
Classifier: Programming Language :: Python :: 3
Classifier: License :: OSI Approved :: GNU Lesser General Public License v3 (LGPLv3)
Classifier: Operating System :: OS Independent
Requires-Dist: sympy
Requires-Dist: ordered-set
Requires-Dist: mistune
Provides-Extra: convert_to_py2
Requires-Dist: 3to2 ; extra == 'convert_to_py2'
Requires-Dist: future (>=0.15.2) ; extra == 'convert_to_py2'
Provides-Extra: docs
Requires-Dist: sphinx ; extra == 'docs'
Provides-Extra: matplotlib
Requires-Dist: matplotlib ; extra == 'matplotlib'
Provides-Extra: matrices
Requires-Dist: numpy ; extra == 'matrices'
Provides-Extra: quantities
Requires-Dist: quantities ; extra == 'quantities'
Requires-Dist: numpy ; extra == 'quantities'
Provides-Extra: testing
Requires-Dist: flake8 (<3.0.0) ; extra == 'testing'
Requires-Dist: pep8-naming (==0.8.2) ; extra == 'testing'
Requires-Dist: flake8-docstrings (==1.3.0) ; extra == 'testing'
Requires-Dist: pycodestyle (==2.0.0) ; extra == 'testing'
Requires-Dist: pydocstyle (==3.0.0) ; extra == 'testing'
Requires-Dist: pyflakes (==1.2.3) ; extra == 'testing'
Requires-Dist: nose ; extra == 'testing'
Requires-Dist: flake8-putty ; extra == 'testing'
Requires-Dist: coverage ; extra == 'testing'
